commonforms/__init__.py
commonforms/__main__.py
commonforms/exceptions.py
commonforms/form_creator.py
commonforms/inference.py
commonforms/utils.py
commonforms-0.1.6.dist-info/METADATA
commonforms-0.1.6.dist-info/WHEEL
commonforms-0.1.6.dist-info/entry_points.txt
commonforms-0.1.6.dist-info/top_level.txt
commonforms-0.1.6.dist-info/RECORD
