Metadata-Version: 2.4
Name: commonforms
Version: 0.1.6
Summary: Automatically convert a PDF into a fillable form
Project-URL: Homepage, https://github.com/jbarrow/commonforms
Requires-Python: >=3.10
Requires-Dist: cryptography>=3.1
Requires-Dist: formalpdf==0.1.6
Requires-Dist: huggingface-hub>=0.35.3
Requires-Dist: onnx>=1.19.1
Requires-Dist: onnxruntime>=1.23.1
Requires-Dist: onnxslim>=0.1.71
Requires-Dist: pillow>=11.3.0
Requires-Dist: pydantic>=2.11.9
Requires-Dist: pypdf>=6.1.1
Requires-Dist: ultralytics>=8.3.204
